polygon_forex_aggregate/__init__.py
polygon_forex_aggregate/currencies.py
polygon_forex_aggregate-0.1.1.dist-info/METADATA
polygon_forex_aggregate-0.1.1.dist-info/WHEEL
polygon_forex_aggregate-0.1.1.dist-info/top_level.txt
polygon_forex_aggregate-0.1.1.dist-info/RECORD
