Metadata-Version: 2.1
Name: polygon-forex-aggregate
Version: 0.1.1
Summary: A currency exchange rate collector using polygon's forex API
Home-page: https://polygon_forex_aggregate.readthedocs.io/
Author: Kuanzhi Wang
Author-email: kw3075@nyu.edu
License: MIT
Platform: UNKNOWN
Classifier: Intended Audience :: Developers
Classifier: License :: OSI Approved :: MIT License
Classifier: Programming Language :: Python
Classifier: Programming Language :: Python :: 3
Classifier: Programming Language :: Python :: 3.6
Classifier: Programming Language :: Python :: 3.7
Classifier: Programming Language :: Python :: 3.8
Classifier: Programming Language :: Python :: 3.9
Classifier: Operating System :: OS Independent
Requires-Dist: sqlalchemy
